{"cameraMode":{"drawMode":0,"name":"Shaded","section":"Shading Mode"},"sceneLighting":true,"audioPlay":false,"sceneViewState":{"m_AlwaysRefresh":false,"showFog":true,"showSkybox":true,"showFlares":true,"showImageEffects":true,"showParticleSystems":true,"showVisualEffectGraphs":true,"m_FxEnabled":true},"in2DMode":false,"pivot":{"x":362.6096496582031,"y":330.5491943359375,"z":8.37109375},"rotation":{"x":-0.19899584352970124,"y":0.000587936956435442,"z":-0.00007403999916277826,"w":-0.9801141619682312},"size":219.66842651367188,"orthographic":false}